{
  "chatbot": [
    {
      "triggers": ["hi", "hey", "hello"],
      "answers": ["6"]
    },
    {
      "triggers": ["how are you", "how you doing"],
      "answers": ["2"]
    },
    {
      "triggers": ["fear"],
      "answers": ["3"]
    },
    {
      "triggers": ["sad"],
      "answers": ["4"]
    },

    {
      "triggers": ["happy"],
      "answers": ["5"]
    },
    {
      "triggers": ["anger"],
      "answers": ["8"]
    },
    {
      "triggers": ["disgust"],
      "answers": ["10"]
    }
  ],

  "catchall": ["1", "2", "3", "4", "5", "6", "7", "8", "9", "10"]
}
